LICENSE
README.md
pyproject.toml
pbs4py/__init__.py
pbs4py/bsub.py
pbs4py/directory_utils.py
pbs4py/fake_pbs.py
pbs4py/job.py
pbs4py/launcher_base.py
pbs4py/pbs.py
pbs4py/pbs_batch.py
pbs4py/slurm.py
pbs4py.egg-info/PKG-INFO
pbs4py.egg-info/SOURCES.txt
pbs4py.egg-info/dependency_links.txt
pbs4py.egg-info/entry_points.txt
pbs4py.egg-info/requires.txt
pbs4py.egg-info/top_level.txt
pbs4py/scripts/__init__.py
pbs4py/scripts/job_dir.py
pbs4py/scripts/qdel_user_jobs.py
tests/test_bsub.py
tests/test_bsub_regression.py
tests/test_fake_pbs.py
tests/test_job.py
tests/test_launch_base.py
tests/test_pbs.py
tests/test_pbs_batch.py
tests/test_pbs_batch_job.py
tests/test_pbs_header.py
tests/test_pbs_regression.py
tests/test_slurm_header.py
tests/test_slurm_regression.py