Metadata-Version: 2.4
Name: pbs4py
Version: 1.1.0
Summary: PBS scripting utilities
Author-email: Kevin Jacobson <kevin.e.jacobson@nasa.gov>
License: NASA OPEN SOURCE AGREEMENT VERSION 1.3
Requires-Python: >=3.6
License-File: LICENSE
Requires-Dist: numpy
Dynamic: license-file
